{
  "schemaVersion": 1,
  "restaurantId": "anju-dc",
  "retrievedAt": "2026-07-15T06:02:24.000Z",
  "sourceUrls": [
    "https://www.anjurestaurant.com/dine-in",
    "https://www.anjurestaurant.com/brunch",
    "https://www.anjurestaurant.com/happy-hour",
    "https://www.anjurestaurant.com/faq",
    "https://www.anjurestaurant.com/order-online",
    "https://order.toasttab.com/online/anju"
  ],
  "presentationCount": 51,
  "itemCount": 49,
  "categoryCount": 9,
  "dinnerPresentationCount": 26,
  "brunchPresentationCount": 18,
  "happyHourPresentationCount": 7,
  "excludedModifierCount": 13,
  "excludedAlcoholCount": 9,
  "officialIngredientCount": 30,
  "unavailableAllergenCount": 19,
  "excludedModifiers": [
    {
      "name": "+soy marinated chicken",
      "priceText": "6",
      "category": "Anju",
      "sourceUrl": "https://www.anjurestaurant.com/dine-in",
      "kind": "priced-modifier"
    },
    {
      "name": "+shrimp",
      "priceText": "9",
      "category": "Anju",
      "sourceUrl": "https://www.anjurestaurant.com/dine-in",
      "kind": "priced-modifier"
    },
    {
      "name": "add tofu or bulgogi",
      "priceText": "7",
      "category": "Main",
      "sourceUrl": "https://www.anjurestaurant.com/dine-in",
      "kind": "priced-modifier"
    },
    {
      "name": "+soy marinated chicken",
      "priceText": "6",
      "category": "Main",
      "sourceUrl": "https://www.anjurestaurant.com/dine-in",
      "kind": "priced-modifier"
    },
    {
      "name": "+tofu or bulgogi",
      "priceText": "7",
      "category": "Main",
      "sourceUrl": "https://www.anjurestaurant.com/dine-in",
      "kind": "priced-modifier"
    },
    {
      "name": "+shrimp",
      "priceText": "9",
      "category": "Main",
      "sourceUrl": "https://www.anjurestaurant.com/dine-in",
      "kind": "priced-modifier"
    },
    {
      "name": "*add extra patty $4",
      "priceText": null,
      "category": "From the Kitchen",
      "sourceUrl": "https://www.anjurestaurant.com/brunch",
      "kind": "inline-modifier",
      "parentName": "Brunch Smash Burger"
    },
    {
      "name": "*add fried egg $2",
      "priceText": null,
      "category": "From the Kitchen",
      "sourceUrl": "https://www.anjurestaurant.com/brunch",
      "kind": "inline-modifier",
      "parentName": "Brunch Smash Burger"
    },
    {
      "name": "(OPTIONAL sub impossible meat)",
      "priceText": null,
      "category": "From the Kitchen",
      "sourceUrl": "https://www.anjurestaurant.com/brunch",
      "kind": "inline-modifier",
      "parentName": "Brunch Smash Burger"
    },
    {
      "name": "add fried egg",
      "priceText": "2",
      "category": "From the Kitchen",
      "sourceUrl": "https://www.anjurestaurant.com/brunch",
      "kind": "priced-modifier"
    },
    {
      "name": "with Tito’s or Soju",
      "priceText": "14",
      "category": "Beverages",
      "sourceUrl": "https://www.anjurestaurant.com/brunch",
      "kind": "priced-modifier"
    },
    {
      "name": "with Tito’s or Soju",
      "priceText": "14",
      "category": "Beverages",
      "sourceUrl": "https://www.anjurestaurant.com/brunch",
      "kind": "priced-modifier"
    },
    {
      "name": "with Chambord and B&B",
      "priceText": "14",
      "category": "Beverages",
      "sourceUrl": "https://www.anjurestaurant.com/brunch",
      "kind": "priced-modifier"
    }
  ],
  "excludedAlcohol": [
    {
      "name": "Peach Perfect",
      "category": "Beverages",
      "menuKind": "brunch",
      "reason": "alcohol-only menu product"
    },
    {
      "name": "Korea-Jillo",
      "category": "Beverages",
      "menuKind": "brunch",
      "reason": "alcohol-only menu product"
    },
    {
      "name": "Cinnamon Toast Punch",
      "category": "Beverages",
      "menuKind": "brunch",
      "reason": "alcohol-only menu product"
    },
    {
      "name": "Kirin Ichiban Draft",
      "category": "Beverages",
      "menuKind": "happy-hour",
      "reason": "alcohol-only menu product"
    },
    {
      "name": "Shandy",
      "category": "Beverages",
      "menuKind": "happy-hour",
      "reason": "alcohol-only menu product"
    },
    {
      "name": "Soju Spritz",
      "category": "Beverages",
      "menuKind": "happy-hour",
      "reason": "alcohol-only menu product"
    },
    {
      "name": "Blossom Punch",
      "category": "Beverages",
      "menuKind": "happy-hour",
      "reason": "alcohol-only menu product"
    },
    {
      "name": "Red wine",
      "category": "Beverages",
      "menuKind": "happy-hour",
      "reason": "alcohol-only menu product"
    },
    {
      "name": "White Wine",
      "category": "Beverages",
      "menuKind": "happy-hour",
      "reason": "alcohol-only menu product"
    }
  ],
  "sourceWarning": "The current restaurant-issued dinner, brunch, and happy-hour pages define the catalog. The restaurant-linked Toast ordering page is used only for overlapping item details and explicit positive disclosures, not to add takeout-only products. The online FAQ says printed gluten-free, vegetarian, and dairy-free menus exist but does not publish them. Its blanket no-peanut statement conflicts with a current Toast peanut warning and is therefore not used as a negative assurance. No complete allergen matrix or cross-contact disclosure is available online.",
  "items": [
    {
      "id": "chikin",
      "name": "Chikin",
      "category": "Anju",
      "description": "half fried chicken, spicy gochujang glaze, white bbq drizzle",
      "ingredientsText": "half fried chicken, spicy gochujang glaze, white bbq drizzle",
      "prices": [
        {
          "menuKind": "dinner",
          "text": "25"
        }
      ],
      "menuKinds": [
        "dinner"
      ],
      "inlineModifiers": [],
      "isConfigurable": false,
      "allergens": [],
      "mayContain": [],
      "allergenSourceType": "unavailable",
      "sourceType": "restaurant-issued-menu-text",
      "sourceUrls": [
        "https://www.anjurestaurant.com/dine-in"
      ],
      "sourceSummary": "Anju's current restaurant-issued menu does not provide enough item-level detail to assign a fixed major-allergen signal. Missing terms are not negative assurances, and no may-contain claim is invented.",
      "evidence": [
        {
          "sourceKind": "restaurant-issued-menu-text",
          "sourceUrl": "https://www.anjurestaurant.com/dine-in",
          "text": "Anju — Chikin — half fried chicken, spicy gochujang glaze, white bbq drizzle"
        }
      ]
    },
    {
      "id": "jajang-green-beans",
      "name": "Jajang Green Beans",
      "category": "Anju",
      "description": "wok fired green beans tossed in jajangmyeon sauce with crispy onions, scallions, chilis, toasted cashews",
      "ingredientsText": "wok fired green beans tossed in jajangmyeon sauce with crispy onions, scallions, chilis, toasted cashews",
      "prices": [
        {
          "menuKind": "dinner",
          "text": "18"
        }
      ],
      "menuKinds": [
        "dinner"
      ],
      "inlineModifiers": [],
      "isConfigurable": false,
      "allergens": [
        "tree-nut"
      ],
      "mayContain": [],
      "allergenSourceType": "official-ingredients",
      "sourceType": "restaurant-issued-menu-text",
      "sourceUrls": [
        "https://www.anjurestaurant.com/dine-in"
      ],
      "sourceSummary": "Direct ingredient terms from Anju's current restaurant-issued menu and, where applicable, its restaurant-linked Toast catalog were reviewed for positive allergen signals. The sources are not a complete allergen matrix or cross-contact disclosure.",
      "evidence": [
        {
          "sourceKind": "restaurant-issued-menu-text",
          "sourceUrl": "https://www.anjurestaurant.com/dine-in",
          "text": "Anju — Jajang Green Beans — wok fired green beans tossed in jajangmyeon sauce with crispy onions, scallions, chilis, toasted cashews"
        }
      ]
    },
    {
      "id": "k-cobb-salad",
      "name": "K Cobb Salad",
      "category": "Anju",
      "description": "romaine hearts, cucumber, tomato, avocado, bacon, soy-marinated egg, scallions, blue cheese with a perilla goddess dressing",
      "ingredientsText": "romaine hearts, cucumber, tomato, avocado, bacon, soy-marinated egg, scallions, blue cheese with a perilla goddess dressing",
      "prices": [
        {
          "menuKind": "dinner",
          "text": "19"
        }
      ],
      "menuKinds": [
        "dinner"
      ],
      "inlineModifiers": [],
      "isConfigurable": false,
      "allergens": [
        "milk",
        "egg",
        "soy"
      ],
      "mayContain": [],
      "allergenSourceType": "official-ingredients",
      "sourceType": "restaurant-issued-menu-text",
      "sourceUrls": [
        "https://www.anjurestaurant.com/dine-in"
      ],
      "sourceSummary": "Direct ingredient terms from Anju's current restaurant-issued menu and, where applicable, its restaurant-linked Toast catalog were reviewed for positive allergen signals. The sources are not a complete allergen matrix or cross-contact disclosure.",
      "evidence": [
        {
          "sourceKind": "restaurant-issued-menu-text",
          "sourceUrl": "https://www.anjurestaurant.com/dine-in",
          "text": "Anju — K Cobb Salad — romaine hearts, cucumber, tomato, avocado, bacon, soy-marinated egg, scallions, blue cheese with a perilla goddess dressing"
        }
      ]
    },
    {
      "id": "kongguksu",
      "name": "Kongguksu",
      "category": "Anju",
      "description": "chilled sweet corn and tofu cream broth, crab, roasted corn, cherry tomatoes, cucumber, toasted pine nuts, scallion oil, somen noodles",
      "ingredientsText": "chilled sweet corn and tofu cream broth, crab, roasted corn, cherry tomatoes, cucumber, toasted pine nuts, scallion oil, somen noodles",
      "prices": [
        {
          "menuKind": "dinner",
          "text": "26"
        }
      ],
      "menuKinds": [
        "dinner"
      ],
      "inlineModifiers": [],
      "isConfigurable": false,
      "allergens": [
        "wheat",
        "gluten",
        "soy",
        "shellfish",
        "tree-nut"
      ],
      "mayContain": [],
      "allergenSourceType": "official-ingredients",
      "sourceType": "restaurant-issued-menu-text",
      "sourceUrls": [
        "https://www.anjurestaurant.com/dine-in"
      ],
      "sourceSummary": "Direct ingredient terms from Anju's current restaurant-issued menu and, where applicable, its restaurant-linked Toast catalog were reviewed for positive allergen signals. The sources are not a complete allergen matrix or cross-contact disclosure.",
      "evidence": [
        {
          "sourceKind": "restaurant-issued-menu-text",
          "sourceUrl": "https://www.anjurestaurant.com/dine-in",
          "text": "Anju — Kongguksu — chilled sweet corn and tofu cream broth, crab, roasted corn, cherry tomatoes, cucumber, toasted pine nuts, scallion oil, somen noodles"
        }
      ]
    },
    {
      "id": "lobster-gyeran-jjim",
      "name": "Lobster Gyeran-Jjim",
      "category": "Anju",
      "description": "steamed korean egg custard with lobster stock, maine lobster, onion, zucchini, sweet peppers, sweet soy glaze",
      "ingredientsText": "steamed korean egg custard with lobster stock, maine lobster, onion, zucchini, sweet peppers, sweet soy glaze",
      "prices": [
        {
          "menuKind": "dinner",
          "text": "24"
        }
      ],
      "menuKinds": [
        "dinner"
      ],
      "inlineModifiers": [],
      "isConfigurable": false,
      "allergens": [
        "egg",
        "soy",
        "shellfish"
      ],
      "mayContain": [],
      "allergenSourceType": "official-ingredients",
      "sourceType": "restaurant-issued-menu-text",
      "sourceUrls": [
        "https://www.anjurestaurant.com/dine-in"
      ],
      "sourceSummary": "Direct ingredient terms from Anju's current restaurant-issued menu and, where applicable, its restaurant-linked Toast catalog were reviewed for positive allergen signals. The sources are not a complete allergen matrix or cross-contact disclosure.",
      "evidence": [
        {
          "sourceKind": "restaurant-issued-menu-text",
          "sourceUrl": "https://www.anjurestaurant.com/dine-in",
          "text": "Anju — Lobster Gyeran-Jjim — steamed korean egg custard with lobster stock, maine lobster, onion, zucchini, sweet peppers, sweet soy glaze"
        }
      ]
    },
    {
      "id": "mandu",
      "name": "Mandu",
      "category": "Anju",
      "description": "pork & kimchi dumplings, pan-fried",
      "ingredientsText": "pork & kimchi dumplings, pan-fried Mandu — pork and kimchi dumplings, served with a sweet soy dipping sauce — contains shellfish",
      "prices": [
        {
          "menuKind": "dinner",
          "text": "16"
        },
        {
          "menuKind": "happy-hour",
          "text": "3 PCS $6"
        }
      ],
      "menuKinds": [
        "dinner",
        "happy-hour"
      ],
      "inlineModifiers": [],
      "isConfigurable": false,
      "allergens": [
        "shellfish",
        "soy"
      ],
      "mayContain": [],
      "allergenSourceType": "official-ingredients",
      "sourceType": "restaurant-issued-menu-and-linked-order-text",
      "sourceUrls": [
        "https://www.anjurestaurant.com/dine-in",
        "https://www.anjurestaurant.com/happy-hour",
        "https://order.toasttab.com/online/anju"
      ],
      "sourceSummary": "Direct ingredient terms from Anju's current restaurant-issued menu and, where applicable, its restaurant-linked Toast catalog were reviewed for positive allergen signals. The sources are not a complete allergen matrix or cross-contact disclosure.",
      "evidence": [
        {
          "sourceKind": "restaurant-issued-menu-text",
          "sourceUrl": "https://www.anjurestaurant.com/dine-in",
          "text": "Anju — Mandu — pork & kimchi dumplings, pan-fried"
        },
        {
          "sourceKind": "restaurant-issued-menu-text",
          "sourceUrl": "https://www.anjurestaurant.com/happy-hour",
          "text": "Anju — Mandu — pork & kimchi dumplings, pan-fried"
        },
        {
          "sourceKind": "restaurant-linked-order-text",
          "sourceUrl": "https://order.toasttab.com/online/anju",
          "text": "Mandu — pork and kimchi dumplings, served with a sweet soy dipping sauce — contains shellfish"
        }
      ]
    },
    {
      "id": "yache-mandu",
      "name": "Yache Mandu",
      "category": "Anju",
      "description": "impossible meat dumpling, chili crunch",
      "ingredientsText": "impossible meat dumpling, chili crunch",
      "prices": [
        {
          "menuKind": "dinner",
          "text": "17"
        },
        {
          "menuKind": "happy-hour",
          "text": "2 PCS $6"
        }
      ],
      "menuKinds": [
        "dinner",
        "happy-hour"
      ],
      "inlineModifiers": [],
      "isConfigurable": false,
      "allergens": [],
      "mayContain": [],
      "allergenSourceType": "unavailable",
      "sourceType": "restaurant-issued-menu-text",
      "sourceUrls": [
        "https://www.anjurestaurant.com/dine-in",
        "https://www.anjurestaurant.com/happy-hour"
      ],
      "sourceSummary": "Anju's current restaurant-issued menu does not provide enough item-level detail to assign a fixed major-allergen signal. Missing terms are not negative assurances, and no may-contain claim is invented.",
      "evidence": [
        {
          "sourceKind": "restaurant-issued-menu-text",
          "sourceUrl": "https://www.anjurestaurant.com/dine-in",
          "text": "Anju — Yache Mandu — impossible meat dumpling, chili crunch"
        },
        {
          "sourceKind": "restaurant-issued-menu-text",
          "sourceUrl": "https://www.anjurestaurant.com/happy-hour",
          "text": "Anju — Yache Mandu — impossible meat dumpling, chili crunch"
        }
      ]
    },
    {
      "id": "yukhoe",
      "name": "Yukhoe",
      "category": "Anju",
      "description": "beef tartare, palm sugar, chili basil seeds, pine nuts, lotus crisps",
      "ingredientsText": "beef tartare, palm sugar, chili basil seeds, pine nuts, lotus crisps",
      "prices": [
        {
          "menuKind": "dinner",
          "text": "23"
        }
      ],
      "menuKinds": [
        "dinner"
      ],
      "inlineModifiers": [],
      "isConfigurable": false,
      "allergens": [
        "tree-nut"
      ],
      "mayContain": [],
      "allergenSourceType": "official-ingredients",
      "sourceType": "restaurant-issued-menu-text",
      "sourceUrls": [
        "https://www.anjurestaurant.com/dine-in"
      ],
      "sourceSummary": "Direct ingredient terms from Anju's current restaurant-issued menu and, where applicable, its restaurant-linked Toast catalog were reviewed for positive allergen signals. The sources are not a complete allergen matrix or cross-contact disclosure.",
      "evidence": [
        {
          "sourceKind": "restaurant-issued-menu-text",
          "sourceUrl": "https://www.anjurestaurant.com/dine-in",
          "text": "Anju — Yukhoe — beef tartare, palm sugar, chili basil seeds, pine nuts, lotus crisps"
        }
      ]
    },
    {
      "id": "jjampong",
      "name": "Jjampong",
      "category": "Main",
      "description": "spicy seafood noodle soup with thick wheat noodles, mussels, clams, shrimp, calamari, napa cabbage, onion, zucchini, carrots",
      "ingredientsText": "spicy seafood noodle soup with thick wheat noodles, mussels, clams, shrimp, calamari, napa cabbage, onion, zucchini, carrots",
      "prices": [
        {
          "menuKind": "dinner",
          "text": "45"
        }
      ],
      "menuKinds": [
        "dinner"
      ],
      "inlineModifiers": [],
      "isConfigurable": false,
      "allergens": [
        "wheat",
        "gluten",
        "shellfish"
      ],
      "mayContain": [],
      "allergenSourceType": "official-ingredients",
      "sourceType": "restaurant-issued-menu-text",
      "sourceUrls": [
        "https://www.anjurestaurant.com/dine-in"
      ],
      "sourceSummary": "Direct ingredient terms from Anju's current restaurant-issued menu and, where applicable, its restaurant-linked Toast catalog were reviewed for positive allergen signals. The sources are not a complete allergen matrix or cross-contact disclosure.",
      "evidence": [
        {
          "sourceKind": "restaurant-issued-menu-text",
          "sourceUrl": "https://www.anjurestaurant.com/dine-in",
          "text": "Main — Jjampong — spicy seafood noodle soup with thick wheat noodles, mussels, clams, shrimp, calamari, napa cabbage, onion, zucchini, carrots"
        }
      ]
    },
    {
      "id": "palace-ddukbokgi",
      "name": "Palace Ddukbokgi",
      "category": "Main",
      "description": "rice cakes, green beans, zucchini, carrots, mushrooms, onion, kale, sweet soy",
      "ingredientsText": "rice cakes, green beans, zucchini, carrots, mushrooms, onion, kale, sweet soy",
      "prices": [
        {
          "menuKind": "dinner",
          "text": "27"
        }
      ],
      "menuKinds": [
        "dinner"
      ],
      "inlineModifiers": [],
      "isConfigurable": false,
      "allergens": [
        "soy"
      ],
      "mayContain": [],
      "allergenSourceType": "official-ingredients",
      "sourceType": "restaurant-issued-menu-text",
      "sourceUrls": [
        "https://www.anjurestaurant.com/dine-in"
      ],
      "sourceSummary": "Direct ingredient terms from Anju's current restaurant-issued menu and, where applicable, its restaurant-linked Toast catalog were reviewed for positive allergen signals. The sources are not a complete allergen matrix or cross-contact disclosure.",
      "evidence": [
        {
          "sourceKind": "restaurant-issued-menu-text",
          "sourceUrl": "https://www.anjurestaurant.com/dine-in",
          "text": "Main — Palace Ddukbokgi — rice cakes, green beans, zucchini, carrots, mushrooms, onion, kale, sweet soy"
        }
      ]
    },
    {
      "id": "pork-rib-and-kimchi-fried-rice",
      "name": "Pork Rib & Kimchi Fried Rice",
      "category": "Main",
      "description": "garlic marinated pork, kimchi fried rice, scrambled egg, pa muchim",
      "ingredientsText": "garlic marinated pork, kimchi fried rice, scrambled egg, pa muchim",
      "prices": [
        {
          "menuKind": "dinner",
          "text": "27"
        }
      ],
      "menuKinds": [
        "dinner"
      ],
      "inlineModifiers": [],
      "isConfigurable": false,
      "allergens": [
        "egg"
      ],
      "mayContain": [],
      "allergenSourceType": "official-ingredients",
      "sourceType": "restaurant-issued-menu-text",
      "sourceUrls": [
        "https://www.anjurestaurant.com/dine-in"
      ],
      "sourceSummary": "Direct ingredient terms from Anju's current restaurant-issued menu and, where applicable, its restaurant-linked Toast catalog were reviewed for positive allergen signals. The sources are not a complete allergen matrix or cross-contact disclosure.",
      "evidence": [
        {
          "sourceKind": "restaurant-issued-menu-text",
          "sourceUrl": "https://www.anjurestaurant.com/dine-in",
          "text": "Main — Pork Rib & Kimchi Fried Rice — garlic marinated pork, kimchi fried rice, scrambled egg, pa muchim"
        }
      ]
    },
    {
      "id": "saengseon",
      "name": "Saengseon",
      "category": "Main",
      "description": "battered branzino, braised mu, yangnyeom sauce, herb muchim",
      "ingredientsText": "battered branzino, braised mu, yangnyeom sauce, herb muchim",
      "prices": [
        {
          "menuKind": "dinner",
          "text": "36"
        }
      ],
      "menuKinds": [
        "dinner"
      ],
      "inlineModifiers": [],
      "isConfigurable": false,
      "allergens": [
        "fish"
      ],
      "mayContain": [],
      "allergenSourceType": "official-ingredients",
      "sourceType": "restaurant-issued-menu-text",
      "sourceUrls": [
        "https://www.anjurestaurant.com/dine-in"
      ],
      "sourceSummary": "Direct ingredient terms from Anju's current restaurant-issued menu and, where applicable, its restaurant-linked Toast catalog were reviewed for positive allergen signals. The sources are not a complete allergen matrix or cross-contact disclosure.",
      "evidence": [
        {
          "sourceKind": "restaurant-issued-menu-text",
          "sourceUrl": "https://www.anjurestaurant.com/dine-in",
          "text": "Main — Saengseon — battered branzino, braised mu, yangnyeom sauce, herb muchim"
        }
      ]
    },
    {
      "id": "ssam-board",
      "name": "Ssam Board",
      "category": "Main",
      "description": "10 oz creekstone farms prime galbi, seasonal greens, roasted garlic ssamjang",
      "ingredientsText": "10 oz creekstone farms prime galbi, seasonal greens, roasted garlic ssamjang",
      "prices": [
        {
          "menuKind": "dinner",
          "text": "42"
        }
      ],
      "menuKinds": [
        "dinner"
      ],
      "inlineModifiers": [],
      "isConfigurable": false,
      "allergens": [],
      "mayContain": [],
      "allergenSourceType": "unavailable",
      "sourceType": "restaurant-issued-menu-text",
      "sourceUrls": [
        "https://www.anjurestaurant.com/dine-in"
      ],
      "sourceSummary": "Anju's current restaurant-issued menu does not provide enough item-level detail to assign a fixed major-allergen signal. Missing terms are not negative assurances, and no may-contain claim is invented.",
      "evidence": [
        {
          "sourceKind": "restaurant-issued-menu-text",
          "sourceUrl": "https://www.anjurestaurant.com/dine-in",
          "text": "Main — Ssam Board — 10 oz creekstone farms prime galbi, seasonal greens, roasted garlic ssamjang"
        }
      ]
    },
    {
      "id": "dak-jjim",
      "name": "Dak Jjim",
      "category": "Mama Lee’s Classics",
      "description": "korean chili-braised chicken thighs, potatoes, and onion",
      "ingredientsText": "korean chili-braised chicken thighs, potatoes, and onion",
      "prices": [
        {
          "menuKind": "dinner",
          "text": "26"
        }
      ],
      "menuKinds": [
        "dinner"
      ],
      "inlineModifiers": [],
      "isConfigurable": false,
      "allergens": [],
      "mayContain": [],
      "allergenSourceType": "unavailable",
      "sourceType": "restaurant-issued-menu-text",
      "sourceUrls": [
        "https://www.anjurestaurant.com/dine-in"
      ],
      "sourceSummary": "Anju's current restaurant-issued menu does not provide enough item-level detail to assign a fixed major-allergen signal. Missing terms are not negative assurances, and no may-contain claim is invented.",
      "evidence": [
        {
          "sourceKind": "restaurant-issued-menu-text",
          "sourceUrl": "https://www.anjurestaurant.com/dine-in",
          "text": "Mama Lee’s Classics — Dak Jjim — korean chili-braised chicken thighs, potatoes, and onion"
        }
      ]
    },
    {
      "id": "dolsot-bibim-bap",
      "name": "Dolsot Bibim Bap",
      "category": "Mama Lee’s Classics",
      "description": "hot stone bowl of rice, assorted vegetables, and choice of bulgogi or tofu",
      "ingredientsText": "hot stone bowl of rice, assorted vegetables, and choice of bulgogi or tofu",
      "prices": [
        {
          "menuKind": "dinner",
          "text": "26"
        }
      ],
      "menuKinds": [
        "dinner"
      ],
      "inlineModifiers": [],
      "isConfigurable": true,
      "allergens": [
        "soy"
      ],
      "mayContain": [],
      "allergenSourceType": "official-ingredients",
      "sourceType": "restaurant-issued-menu-text",
      "sourceUrls": [
        "https://www.anjurestaurant.com/dine-in"
      ],
      "sourceSummary": "Direct ingredient terms from Anju's current restaurant-issued menu and, where applicable, its restaurant-linked Toast catalog were reviewed for positive allergen signals. The sources are not a complete allergen matrix or cross-contact disclosure.",
      "evidence": [
        {
          "sourceKind": "restaurant-issued-menu-text",
          "sourceUrl": "https://www.anjurestaurant.com/dine-in",
          "text": "Mama Lee’s Classics — Dolsot Bibim Bap — hot stone bowl of rice, assorted vegetables, and choice of bulgogi or tofu"
        }
      ]
    },
    {
      "id": "kimchi-jjigae",
      "name": "Kimchi Jjigae",
      "category": "Mama Lee’s Classics",
      "description": "braised pork shoulder stew, tofu, aged kimchi",
      "ingredientsText": "braised pork shoulder stew, tofu, aged kimchi",
      "prices": [
        {
          "menuKind": "dinner",
          "text": "26"
        }
      ],
      "menuKinds": [
        "dinner"
      ],
      "inlineModifiers": [],
      "isConfigurable": false,
      "allergens": [
        "soy"
      ],
      "mayContain": [],
      "allergenSourceType": "official-ingredients",
      "sourceType": "restaurant-issued-menu-text",
      "sourceUrls": [
        "https://www.anjurestaurant.com/dine-in"
      ],
      "sourceSummary": "Direct ingredient terms from Anju's current restaurant-issued menu and, where applicable, its restaurant-linked Toast catalog were reviewed for positive allergen signals. The sources are not a complete allergen matrix or cross-contact disclosure.",
      "evidence": [
        {
          "sourceKind": "restaurant-issued-menu-text",
          "sourceUrl": "https://www.anjurestaurant.com/dine-in",
          "text": "Mama Lee’s Classics — Kimchi Jjigae — braised pork shoulder stew, tofu, aged kimchi"
        }
      ]
    },
    {
      "id": "30-day-kimchi",
      "name": "30-Day Kimchi",
      "category": "Panchan",
      "description": null,
      "ingredientsText": null,
      "prices": [
        {
          "menuKind": "dinner",
          "text": "6"
        }
      ],
      "menuKinds": [
        "dinner"
      ],
      "inlineModifiers": [],
      "isConfigurable": false,
      "allergens": [],
      "mayContain": [],
      "allergenSourceType": "unavailable",
      "sourceType": "restaurant-issued-menu-text",
      "sourceUrls": [
        "https://www.anjurestaurant.com/dine-in"
      ],
      "sourceSummary": "Anju's current restaurant-issued menu does not provide enough item-level detail to assign a fixed major-allergen signal. Missing terms are not negative assurances, and no may-contain claim is invented.",
      "evidence": [
        {
          "sourceKind": "restaurant-issued-menu-text",
          "sourceUrl": "https://www.anjurestaurant.com/dine-in",
          "text": "Panchan — 30-Day Kimchi"
        }
      ]
    },
    {
      "id": "eomuk",
      "name": "Eomuk",
      "category": "Panchan",
      "description": null,
      "ingredientsText": "Eomuk — fish cakes with carrots, onion, & peppers",
      "prices": [
        {
          "menuKind": "dinner",
          "text": "6"
        }
      ],
      "menuKinds": [
        "dinner"
      ],
      "inlineModifiers": [],
      "isConfigurable": false,
      "allergens": [
        "fish"
      ],
      "mayContain": [],
      "allergenSourceType": "official-ingredients",
      "sourceType": "restaurant-issued-menu-and-linked-order-text",
      "sourceUrls": [
        "https://www.anjurestaurant.com/dine-in",
        "https://order.toasttab.com/online/anju"
      ],
      "sourceSummary": "Direct ingredient terms from Anju's current restaurant-issued menu and, where applicable, its restaurant-linked Toast catalog were reviewed for positive allergen signals. The sources are not a complete allergen matrix or cross-contact disclosure.",
      "evidence": [
        {
          "sourceKind": "restaurant-issued-menu-text",
          "sourceUrl": "https://www.anjurestaurant.com/dine-in",
          "text": "Panchan — Eomuk"
        },
        {
          "sourceKind": "restaurant-linked-order-text",
          "sourceUrl": "https://order.toasttab.com/online/anju",
          "text": "Eomuk — fish cakes with carrots, onion, & peppers"
        }
      ]
    },
    {
      "id": "pickled-cucumbers",
      "name": "Pickled Cucumbers",
      "category": "Panchan",
      "description": null,
      "ingredientsText": null,
      "prices": [
        {
          "menuKind": "dinner",
          "text": "6"
        }
      ],
      "menuKinds": [
        "dinner"
      ],
      "inlineModifiers": [],
      "isConfigurable": false,
      "allergens": [],
      "mayContain": [],
      "allergenSourceType": "unavailable",
      "sourceType": "restaurant-issued-menu-text",
      "sourceUrls": [
        "https://www.anjurestaurant.com/dine-in"
      ],
      "sourceSummary": "Anju's current restaurant-issued menu does not provide enough item-level detail to assign a fixed major-allergen signal. Missing terms are not negative assurances, and no may-contain claim is invented.",
      "evidence": [
        {
          "sourceKind": "restaurant-issued-menu-text",
          "sourceUrl": "https://www.anjurestaurant.com/dine-in",
          "text": "Panchan — Pickled Cucumbers"
        }
      ]
    },
    {
      "id": "set-of-three-choose-any-3",
      "name": "Set of Three (Choose any 3)",
      "category": "Panchan",
      "description": null,
      "ingredientsText": null,
      "prices": [
        {
          "menuKind": "dinner",
          "text": "15"
        }
      ],
      "menuKinds": [
        "dinner"
      ],
      "inlineModifiers": [],
      "isConfigurable": true,
      "allergens": [],
      "mayContain": [],
      "allergenSourceType": "unavailable",
      "sourceType": "restaurant-issued-menu-text",
      "sourceUrls": [
        "https://www.anjurestaurant.com/dine-in"
      ],
      "sourceSummary": "Anju's current restaurant-issued menu does not provide enough item-level detail to assign a fixed major-allergen signal. Missing terms are not negative assurances, and no may-contain claim is invented.",
      "evidence": [
        {
          "sourceKind": "restaurant-issued-menu-text",
          "sourceUrl": "https://www.anjurestaurant.com/dine-in",
          "text": "Panchan — Set of Three (Choose any 3)"
        }
      ]
    },
    {
      "id": "soy-brined-chayote",
      "name": "Soy-brined Chayote",
      "category": "Panchan",
      "description": null,
      "ingredientsText": null,
      "prices": [
        {
          "menuKind": "dinner",
          "text": "6"
        }
      ],
      "menuKinds": [
        "dinner"
      ],
      "inlineModifiers": [],
      "isConfigurable": false,
      "allergens": [
        "soy"
      ],
      "mayContain": [],
      "allergenSourceType": "official-ingredients",
      "sourceType": "restaurant-issued-menu-text",
      "sourceUrls": [
        "https://www.anjurestaurant.com/dine-in"
      ],
      "sourceSummary": "Direct ingredient terms from Anju's current restaurant-issued menu and, where applicable, its restaurant-linked Toast catalog were reviewed for positive allergen signals. The sources are not a complete allergen matrix or cross-contact disclosure.",
      "evidence": [
        {
          "sourceKind": "restaurant-issued-menu-text",
          "sourceUrl": "https://www.anjurestaurant.com/dine-in",
          "text": "Panchan — Soy-brined Chayote"
        }
      ]
    },
    {
      "id": "sweet-lotus-root",
      "name": "Sweet Lotus Root",
      "category": "Panchan",
      "description": null,
      "ingredientsText": null,
      "prices": [
        {
          "menuKind": "dinner",
          "text": "6"
        }
      ],
      "menuKinds": [
        "dinner"
      ],
      "inlineModifiers": [],
      "isConfigurable": false,
      "allergens": [],
      "mayContain": [],
      "allergenSourceType": "unavailable",
      "sourceType": "restaurant-issued-menu-text",
      "sourceUrls": [
        "https://www.anjurestaurant.com/dine-in"
      ],
      "sourceSummary": "Anju's current restaurant-issued menu does not provide enough item-level detail to assign a fixed major-allergen signal. Missing terms are not negative assurances, and no may-contain claim is invented.",
      "evidence": [
        {
          "sourceKind": "restaurant-issued-menu-text",
          "sourceUrl": "https://www.anjurestaurant.com/dine-in",
          "text": "Panchan — Sweet Lotus Root"
        }
      ]
    },
    {
      "id": "yeolmu-kimchi",
      "name": "Yeolmu Kimchi",
      "category": "Panchan",
      "description": null,
      "ingredientsText": null,
      "prices": [
        {
          "menuKind": "dinner",
          "text": "6"
        }
      ],
      "menuKinds": [
        "dinner"
      ],
      "inlineModifiers": [],
      "isConfigurable": false,
      "allergens": [],
      "mayContain": [],
      "allergenSourceType": "unavailable",
      "sourceType": "restaurant-issued-menu-text",
      "sourceUrls": [
        "https://www.anjurestaurant.com/dine-in"
      ],
      "sourceSummary": "Anju's current restaurant-issued menu does not provide enough item-level detail to assign a fixed major-allergen signal. Missing terms are not negative assurances, and no may-contain claim is invented.",
      "evidence": [
        {
          "sourceKind": "restaurant-issued-menu-text",
          "sourceUrl": "https://www.anjurestaurant.com/dine-in",
          "text": "Panchan — Yeolmu Kimchi"
        }
      ]
    },
    {
      "id": "banana-milk-parfait",
      "name": "Banana Milk Parfait",
      "category": "Dessert",
      "description": "layers of banana custard, fresh bananas, caramel, black sesame praline, vanilla wafers, dulce de leche gelato",
      "ingredientsText": "layers of banana custard, fresh bananas, caramel, black sesame praline, vanilla wafers, dulce de leche gelato",
      "prices": [
        {
          "menuKind": "dinner",
          "text": "16"
        }
      ],
      "menuKinds": [
        "dinner"
      ],
      "inlineModifiers": [],
      "isConfigurable": false,
      "allergens": [
        "milk",
        "wheat",
        "gluten",
        "sesame"
      ],
      "mayContain": [],
      "allergenSourceType": "official-ingredients",
      "sourceType": "restaurant-issued-menu-text",
      "sourceUrls": [
        "https://www.anjurestaurant.com/dine-in"
      ],
      "sourceSummary": "Direct ingredient terms from Anju's current restaurant-issued menu and, where applicable, its restaurant-linked Toast catalog were reviewed for positive allergen signals. The sources are not a complete allergen matrix or cross-contact disclosure.",
      "evidence": [
        {
          "sourceKind": "restaurant-issued-menu-text",
          "sourceUrl": "https://www.anjurestaurant.com/dine-in",
          "text": "Dessert — Banana Milk Parfait — layers of banana custard, fresh bananas, caramel, black sesame praline, vanilla wafers, dulce de leche gelato"
        }
      ]
    },
    {
      "id": "sorbet-or-gelato",
      "name": "Sorbet or Gelato",
      "category": "Dessert",
      "description": "gelato - black sesame or french vanilla or dulce de leche sorbet - seasonal",
      "ingredientsText": "gelato - black sesame or french vanilla or dulce de leche sorbet - seasonal",
      "prices": [
        {
          "menuKind": "dinner",
          "text": "5"
        }
      ],
      "menuKinds": [
        "dinner"
      ],
      "inlineModifiers": [],
      "isConfigurable": true,
      "allergens": [
        "milk",
        "sesame"
      ],
      "mayContain": [],
      "allergenSourceType": "official-ingredients",
      "sourceType": "restaurant-issued-menu-text",
      "sourceUrls": [
        "https://www.anjurestaurant.com/dine-in"
      ],
      "sourceSummary": "Direct ingredient terms from Anju's current restaurant-issued menu and, where applicable, its restaurant-linked Toast catalog were reviewed for positive allergen signals. The sources are not a complete allergen matrix or cross-contact disclosure.",
      "evidence": [
        {
          "sourceKind": "restaurant-issued-menu-text",
          "sourceUrl": "https://www.anjurestaurant.com/dine-in",
          "text": "Dessert — Sorbet or Gelato — gelato - black sesame or french vanilla or dulce de leche sorbet - seasonal"
        }
      ]
    },
    {
      "id": "summer-bingsu",
      "name": "Summer Bingsu",
      "category": "Dessert",
      "description": "limeade shaved ice with fresh watermelon, berries, condensed milk, french vanilla gelato, whipped cream",
      "ingredientsText": "limeade shaved ice with fresh watermelon, berries, condensed milk, french vanilla gelato, whipped cream",
      "prices": [
        {
          "menuKind": "dinner",
          "text": "16"
        }
      ],
      "menuKinds": [
        "dinner"
      ],
      "inlineModifiers": [],
      "isConfigurable": false,
      "allergens": [
        "milk"
      ],
      "mayContain": [],
      "allergenSourceType": "official-ingredients",
      "sourceType": "restaurant-issued-menu-text",
      "sourceUrls": [
        "https://www.anjurestaurant.com/dine-in"
      ],
      "sourceSummary": "Direct ingredient terms from Anju's current restaurant-issued menu and, where applicable, its restaurant-linked Toast catalog were reviewed for positive allergen signals. The sources are not a complete allergen matrix or cross-contact disclosure.",
      "evidence": [
        {
          "sourceKind": "restaurant-issued-menu-text",
          "sourceUrl": "https://www.anjurestaurant.com/dine-in",
          "text": "Dessert — Summer Bingsu — limeade shaved ice with fresh watermelon, berries, condensed milk, french vanilla gelato, whipped cream"
        }
      ]
    },
    {
      "id": "berry-matcha-parfait",
      "name": "Berry Matcha Parfait",
      "category": "From the Kitchen",
      "description": "matcha yogurt with strawberry preserves, fresh berries, pistachio, granola, whipped cream",
      "ingredientsText": "matcha yogurt with strawberry preserves, fresh berries, pistachio, granola, whipped cream",
      "prices": [
        {
          "menuKind": "brunch",
          "text": "9"
        }
      ],
      "menuKinds": [
        "brunch"
      ],
      "inlineModifiers": [],
      "isConfigurable": false,
      "allergens": [
        "milk",
        "tree-nut"
      ],
      "mayContain": [],
      "allergenSourceType": "official-ingredients",
      "sourceType": "restaurant-issued-menu-text",
      "sourceUrls": [
        "https://www.anjurestaurant.com/brunch"
      ],
      "sourceSummary": "Direct ingredient terms from Anju's current restaurant-issued menu and, where applicable, its restaurant-linked Toast catalog were reviewed for positive allergen signals. The sources are not a complete allergen matrix or cross-contact disclosure.",
      "evidence": [
        {
          "sourceKind": "restaurant-issued-menu-text",
          "sourceUrl": "https://www.anjurestaurant.com/brunch",
          "text": "From the Kitchen — Berry Matcha Parfait — matcha yogurt with strawberry preserves, fresh berries, pistachio, granola, whipped cream"
        }
      ]
    },
    {
      "id": "brunch-smash-burger",
      "name": "Brunch Smash Burger",
      "category": "From the Kitchen",
      "description": "smashed kalbi-spiced short rib patty, tomato, lettuce, American cheese, candied chilies, onion ring, Seoul sauce on a toasted bun",
      "ingredientsText": "smashed kalbi-spiced short rib patty, tomato, lettuce, American cheese, candied chilies, onion ring, Seoul sauce on a toasted bun",
      "prices": [
        {
          "menuKind": "brunch",
          "text": "16"
        }
      ],
      "menuKinds": [
        "brunch"
      ],
      "inlineModifiers": [
        "*add extra patty $4",
        "*add fried egg $2",
        "(OPTIONAL sub impossible meat)"
      ],
      "isConfigurable": true,
      "allergens": [
        "milk",
        "wheat",
        "gluten"
      ],
      "mayContain": [],
      "allergenSourceType": "official-ingredients",
      "sourceType": "restaurant-issued-menu-text",
      "sourceUrls": [
        "https://www.anjurestaurant.com/brunch"
      ],
      "sourceSummary": "Direct ingredient terms from Anju's current restaurant-issued menu and, where applicable, its restaurant-linked Toast catalog were reviewed for positive allergen signals. The sources are not a complete allergen matrix or cross-contact disclosure.",
      "evidence": [
        {
          "sourceKind": "restaurant-issued-menu-text",
          "sourceUrl": "https://www.anjurestaurant.com/brunch",
          "text": "From the Kitchen — Brunch Smash Burger — smashed kalbi-spiced short rib patty, tomato, lettuce, American cheese, candied chilies, onion ring, Seoul sauce on a toasted bun"
        }
      ]
    },
    {
      "id": "buchu-jeon-waffle-and-mala-fried-chicken",
      "name": "Buchu Jeon Waffle & Mala Fried Chicken",
      "category": "From the Kitchen",
      "description": "savory garlic chive waffle with crispy mala-spiced fried chicken, finished with hot honey",
      "ingredientsText": "savory garlic chive waffle with crispy mala-spiced fried chicken, finished with hot honey",
      "prices": [
        {
          "menuKind": "brunch",
          "text": "28"
        }
      ],
      "menuKinds": [
        "brunch"
      ],
      "inlineModifiers": [],
      "isConfigurable": false,
      "allergens": [
        "wheat",
        "gluten"
      ],
      "mayContain": [],
      "allergenSourceType": "official-ingredients",
      "sourceType": "restaurant-issued-menu-text",
      "sourceUrls": [
        "https://www.anjurestaurant.com/brunch"
      ],
      "sourceSummary": "Direct ingredient terms from Anju's current restaurant-issued menu and, where applicable, its restaurant-linked Toast catalog were reviewed for positive allergen signals. The sources are not a complete allergen matrix or cross-contact disclosure.",
      "evidence": [
        {
          "sourceKind": "restaurant-issued-menu-text",
          "sourceUrl": "https://www.anjurestaurant.com/brunch",
          "text": "From the Kitchen — Buchu Jeon Waffle & Mala Fried Chicken — savory garlic chive waffle with crispy mala-spiced fried chicken, finished with hot honey"
        }
      ]
    },
    {
      "id": "gimbap-box",
      "name": "Gimbap Box",
      "category": "From the Kitchen",
      "description": "build-your-own gimbap: gim, seasoned rice, avocado, bellflower root, danmuji, kimchi, cucumber, tuna, panko crusted shrimp, served with soy dipping sauce, sriracha mayo",
      "ingredientsText": "build-your-own gimbap: gim, seasoned rice, avocado, bellflower root, danmuji, kimchi, cucumber, tuna, panko crusted shrimp, served with soy dipping sauce, sriracha mayo",
      "prices": [
        {
          "menuKind": "brunch",
          "text": "28"
        }
      ],
      "menuKinds": [
        "brunch"
      ],
      "inlineModifiers": [],
      "isConfigurable": true,
      "allergens": [
        "wheat",
        "gluten",
        "egg",
        "soy",
        "fish",
        "shellfish"
      ],
      "mayContain": [],
      "allergenSourceType": "official-ingredients",
      "sourceType": "restaurant-issued-menu-text",
      "sourceUrls": [
        "https://www.anjurestaurant.com/brunch"
      ],
      "sourceSummary": "Direct ingredient terms from Anju's current restaurant-issued menu and, where applicable, its restaurant-linked Toast catalog were reviewed for positive allergen signals. The sources are not a complete allergen matrix or cross-contact disclosure.",
      "evidence": [
        {
          "sourceKind": "restaurant-issued-menu-text",
          "sourceUrl": "https://www.anjurestaurant.com/brunch",
          "text": "From the Kitchen — Gimbap Box — build-your-own gimbap: gim, seasoned rice, avocado, bellflower root, danmuji, kimchi, cucumber, tuna, panko crusted shrimp, served with soy dipping sauce, sriracha mayo"
        }
      ]
    },
    {
      "id": "grilled-kalbi-and-eggs",
      "name": "Grilled Kalbi & Eggs",
      "category": "From the Kitchen",
      "description": "soy marinated grilled short rib, furikake rice, sunny side up eggs",
      "ingredientsText": "soy marinated grilled short rib, furikake rice, sunny side up eggs",
      "prices": [
        {
          "menuKind": "brunch",
          "text": "30"
        }
      ],
      "menuKinds": [
        "brunch"
      ],
      "inlineModifiers": [],
      "isConfigurable": false,
      "allergens": [
        "egg",
        "soy"
      ],
      "mayContain": [],
      "allergenSourceType": "official-ingredients",
      "sourceType": "restaurant-issued-menu-text",
      "sourceUrls": [
        "https://www.anjurestaurant.com/brunch"
      ],
      "sourceSummary": "Direct ingredient terms from Anju's current restaurant-issued menu and, where applicable, its restaurant-linked Toast catalog were reviewed for positive allergen signals. The sources are not a complete allergen matrix or cross-contact disclosure.",
      "evidence": [
        {
          "sourceKind": "restaurant-issued-menu-text",
          "sourceUrl": "https://www.anjurestaurant.com/brunch",
          "text": "From the Kitchen — Grilled Kalbi & Eggs — soy marinated grilled short rib, furikake rice, sunny side up eggs"
        }
      ]
    },
    {
      "id": "hansik-jeongsik",
      "name": "Hansik Jeongsik",
      "category": "From the Kitchen",
      "description": "gochujang marinated grilled pork belly, doenjang-jjigae, gyeran mari, seasonal banchan, rice",
      "ingredientsText": "gochujang marinated grilled pork belly, doenjang-jjigae, gyeran mari, seasonal banchan, rice",
      "prices": [
        {
          "menuKind": "brunch",
          "text": "25"
        }
      ],
      "menuKinds": [
        "brunch"
      ],
      "inlineModifiers": [],
      "isConfigurable": false,
      "allergens": [
        "egg"
      ],
      "mayContain": [],
      "allergenSourceType": "official-ingredients",
      "sourceType": "restaurant-issued-menu-text",
      "sourceUrls": [
        "https://www.anjurestaurant.com/brunch"
      ],
      "sourceSummary": "Direct ingredient terms from Anju's current restaurant-issued menu and, where applicable, its restaurant-linked Toast catalog were reviewed for positive allergen signals. The sources are not a complete allergen matrix or cross-contact disclosure.",
      "evidence": [
        {
          "sourceKind": "restaurant-issued-menu-text",
          "sourceUrl": "https://www.anjurestaurant.com/brunch",
          "text": "From the Kitchen — Hansik Jeongsik — gochujang marinated grilled pork belly, doenjang-jjigae, gyeran mari, seasonal banchan, rice"
        }
      ]
    },
    {
      "id": "peach-and-pecan-pancakes",
      "name": "Peach & Pecan Pancakes",
      "category": "From the Kitchen",
      "description": "two fluffy pancakes, peaches, spiced pecans, warm cinnamon brown sugar syrup, whipped cream, injeolmi powder",
      "ingredientsText": "two fluffy pancakes, peaches, spiced pecans, warm cinnamon brown sugar syrup, whipped cream, injeolmi powder",
      "prices": [
        {
          "menuKind": "brunch",
          "text": "17"
        }
      ],
      "menuKinds": [
        "brunch"
      ],
      "inlineModifiers": [],
      "isConfigurable": false,
      "allergens": [
        "milk",
        "wheat",
        "gluten",
        "tree-nut"
      ],
      "mayContain": [],
      "allergenSourceType": "official-ingredients",
      "sourceType": "restaurant-issued-menu-text",
      "sourceUrls": [
        "https://www.anjurestaurant.com/brunch"
      ],
      "sourceSummary": "Direct ingredient terms from Anju's current restaurant-issued menu and, where applicable, its restaurant-linked Toast catalog were reviewed for positive allergen signals. The sources are not a complete allergen matrix or cross-contact disclosure.",
      "evidence": [
        {
          "sourceKind": "restaurant-issued-menu-text",
          "sourceUrl": "https://www.anjurestaurant.com/brunch",
          "text": "From the Kitchen — Peach & Pecan Pancakes — two fluffy pancakes, peaches, spiced pecans, warm cinnamon brown sugar syrup, whipped cream, injeolmi powder"
        }
      ]
    },
    {
      "id": "salmon-blt",
      "name": "Salmon “BLT”",
      "category": "From the Kitchen",
      "description": "pan-seared salmon, arugula, heirloom tomato, hickory bacon, charred long pepper aioli on toasted sourdough",
      "ingredientsText": "pan-seared salmon, arugula, heirloom tomato, hickory bacon, charred long pepper aioli on toasted sourdough",
      "prices": [
        {
          "menuKind": "brunch",
          "text": "22"
        }
      ],
      "menuKinds": [
        "brunch"
      ],
      "inlineModifiers": [],
      "isConfigurable": false,
      "allergens": [
        "wheat",
        "gluten",
        "egg",
        "fish"
      ],
      "mayContain": [],
      "allergenSourceType": "official-ingredients",
      "sourceType": "restaurant-issued-menu-text",
      "sourceUrls": [
        "https://www.anjurestaurant.com/brunch"
      ],
      "sourceSummary": "Direct ingredient terms from Anju's current restaurant-issued menu and, where applicable, its restaurant-linked Toast catalog were reviewed for positive allergen signals. The sources are not a complete allergen matrix or cross-contact disclosure.",
      "evidence": [
        {
          "sourceKind": "restaurant-issued-menu-text",
          "sourceUrl": "https://www.anjurestaurant.com/brunch",
          "text": "From the Kitchen — Salmon “BLT” — pan-seared salmon, arugula, heirloom tomato, hickory bacon, charred long pepper aioli on toasted sourdough"
        }
      ]
    },
    {
      "id": "shrimp-juk",
      "name": "Shrimp Juk",
      "category": "From the Kitchen",
      "description": "goguma rice porridge with scallions, sesame oil, toasted sesame seeds, served with grilled shrimp, perilla pesto (vegetarian- with tofu)",
      "ingredientsText": "goguma rice porridge with scallions, sesame oil, toasted sesame seeds, served with grilled shrimp, perilla pesto (vegetarian- with tofu)",
      "prices": [
        {
          "menuKind": "brunch",
          "text": "22"
        }
      ],
      "menuKinds": [
        "brunch"
      ],
      "inlineModifiers": [],
      "isConfigurable": true,
      "allergens": [
        "soy",
        "shellfish",
        "sesame"
      ],
      "mayContain": [],
      "allergenSourceType": "official-ingredients",
      "sourceType": "restaurant-issued-menu-text",
      "sourceUrls": [
        "https://www.anjurestaurant.com/brunch"
      ],
      "sourceSummary": "Direct ingredient terms from Anju's current restaurant-issued menu and, where applicable, its restaurant-linked Toast catalog were reviewed for positive allergen signals. The sources are not a complete allergen matrix or cross-contact disclosure.",
      "evidence": [
        {
          "sourceKind": "restaurant-issued-menu-text",
          "sourceUrl": "https://www.anjurestaurant.com/brunch",
          "text": "From the Kitchen — Shrimp Juk — goguma rice porridge with scallions, sesame oil, toasted sesame seeds, served with grilled shrimp, perilla pesto (vegetarian- with tofu)"
        }
      ]
    },
    {
      "id": "winter-salad",
      "name": "Winter Salad",
      "category": "From the Kitchen",
      "description": "fall mixed greens, spiced pecans, pear, cherry tomato, smoked applewood bacon, pickled red onion, doenjang blue cheese dressing, mandu crisps",
      "ingredientsText": "fall mixed greens, spiced pecans, pear, cherry tomato, smoked applewood bacon, pickled red onion, doenjang blue cheese dressing, mandu crisps",
      "prices": [
        {
          "menuKind": "brunch",
          "text": "16"
        }
      ],
      "menuKinds": [
        "brunch"
      ],
      "inlineModifiers": [],
      "isConfigurable": false,
      "allergens": [
        "milk",
        "wheat",
        "gluten",
        "tree-nut"
      ],
      "mayContain": [],
      "allergenSourceType": "official-ingredients",
      "sourceType": "restaurant-issued-menu-text",
      "sourceUrls": [
        "https://www.anjurestaurant.com/brunch"
      ],
      "sourceSummary": "Direct ingredient terms from Anju's current restaurant-issued menu and, where applicable, its restaurant-linked Toast catalog were reviewed for positive allergen signals. The sources are not a complete allergen matrix or cross-contact disclosure.",
      "evidence": [
        {
          "sourceKind": "restaurant-issued-menu-text",
          "sourceUrl": "https://www.anjurestaurant.com/brunch",
          "text": "From the Kitchen — Winter Salad — fall mixed greens, spiced pecans, pear, cherry tomato, smoked applewood bacon, pickled red onion, doenjang blue cheese dressing, mandu crisps"
        }
      ]
    },
    {
      "id": "doenjang-jjigae",
      "name": "Doenjang- Jjigae",
      "category": "Add Ons",
      "description": "soy bean soup, scallion, onion, zucchini, potato",
      "ingredientsText": "soy bean soup, scallion, onion, zucchini, potato",
      "prices": [
        {
          "menuKind": "brunch",
          "text": "6"
        }
      ],
      "menuKinds": [
        "brunch"
      ],
      "inlineModifiers": [],
      "isConfigurable": false,
      "allergens": [
        "soy"
      ],
      "mayContain": [],
      "allergenSourceType": "official-ingredients",
      "sourceType": "restaurant-issued-menu-text",
      "sourceUrls": [
        "https://www.anjurestaurant.com/brunch"
      ],
      "sourceSummary": "Direct ingredient terms from Anju's current restaurant-issued menu and, where applicable, its restaurant-linked Toast catalog were reviewed for positive allergen signals. The sources are not a complete allergen matrix or cross-contact disclosure.",
      "evidence": [
        {
          "sourceKind": "restaurant-issued-menu-text",
          "sourceUrl": "https://www.anjurestaurant.com/brunch",
          "text": "Add Ons — Doenjang- Jjigae — soy bean soup, scallion, onion, zucchini, potato"
        }
      ]
    },
    {
      "id": "juk",
      "name": "Juk",
      "category": "Add Ons",
      "description": "rice porridge, scallion, crispy shallots",
      "ingredientsText": "rice porridge, scallion, crispy shallots",
      "prices": [
        {
          "menuKind": "brunch",
          "text": "5"
        }
      ],
      "menuKinds": [
        "brunch"
      ],
      "inlineModifiers": [],
      "isConfigurable": false,
      "allergens": [],
      "mayContain": [],
      "allergenSourceType": "unavailable",
      "sourceType": "restaurant-issued-menu-text",
      "sourceUrls": [
        "https://www.anjurestaurant.com/brunch"
      ],
      "sourceSummary": "Anju's current restaurant-issued menu does not provide enough item-level detail to assign a fixed major-allergen signal. Missing terms are not negative assurances, and no may-contain claim is invented.",
      "evidence": [
        {
          "sourceKind": "restaurant-issued-menu-text",
          "sourceUrl": "https://www.anjurestaurant.com/brunch",
          "text": "Add Ons — Juk — rice porridge, scallion, crispy shallots"
        }
      ]
    },
    {
      "id": "loaded-tater-tots",
      "name": "Loaded Tater Tots",
      "category": "Add Ons",
      "description": "bulgogi, kimchi, cass beer cheese",
      "ingredientsText": "bulgogi, kimchi, cass beer cheese",
      "prices": [
        {
          "menuKind": "brunch",
          "text": "small 7, large 12"
        }
      ],
      "menuKinds": [
        "brunch"
      ],
      "inlineModifiers": [],
      "isConfigurable": false,
      "allergens": [
        "milk"
      ],
      "mayContain": [],
      "allergenSourceType": "official-ingredients",
      "sourceType": "restaurant-issued-menu-text",
      "sourceUrls": [
        "https://www.anjurestaurant.com/brunch"
      ],
      "sourceSummary": "Direct ingredient terms from Anju's current restaurant-issued menu and, where applicable, its restaurant-linked Toast catalog were reviewed for positive allergen signals. The sources are not a complete allergen matrix or cross-contact disclosure.",
      "evidence": [
        {
          "sourceKind": "restaurant-issued-menu-text",
          "sourceUrl": "https://www.anjurestaurant.com/brunch",
          "text": "Add Ons — Loaded Tater Tots — bulgogi, kimchi, cass beer cheese"
        }
      ]
    },
    {
      "id": "tater-tots",
      "name": "Tater Tots",
      "category": "Add Ons",
      "description": "anju salt, scallions",
      "ingredientsText": "anju salt, scallions",
      "prices": [
        {
          "menuKind": "brunch",
          "text": "small 5, large 8"
        }
      ],
      "menuKinds": [
        "brunch"
      ],
      "inlineModifiers": [],
      "isConfigurable": false,
      "allergens": [],
      "mayContain": [],
      "allergenSourceType": "unavailable",
      "sourceType": "restaurant-issued-menu-text",
      "sourceUrls": [
        "https://www.anjurestaurant.com/brunch"
      ],
      "sourceSummary": "Anju's current restaurant-issued menu does not provide enough item-level detail to assign a fixed major-allergen signal. Missing terms are not negative assurances, and no may-contain claim is invented.",
      "evidence": [
        {
          "sourceKind": "restaurant-issued-menu-text",
          "sourceUrl": "https://www.anjurestaurant.com/brunch",
          "text": "Add Ons — Tater Tots — anju salt, scallions"
        }
      ]
    },
    {
      "id": "bulgogi-frito-pie",
      "name": "Bulgogi Frito Pie",
      "category": "Happy Hour",
      "description": "bulgogi, kimchi slaw, lime sour cream, scallions, sesame seeds, crispy onions",
      "ingredientsText": "bulgogi, kimchi slaw, lime sour cream, scallions, sesame seeds, crispy onions",
      "prices": [
        {
          "menuKind": "happy-hour",
          "text": "$8"
        }
      ],
      "menuKinds": [
        "happy-hour"
      ],
      "inlineModifiers": [],
      "isConfigurable": false,
      "allergens": [
        "milk",
        "sesame"
      ],
      "mayContain": [],
      "allergenSourceType": "official-ingredients",
      "sourceType": "restaurant-issued-menu-text",
      "sourceUrls": [
        "https://www.anjurestaurant.com/happy-hour"
      ],
      "sourceSummary": "Direct ingredient terms from Anju's current restaurant-issued menu and, where applicable, its restaurant-linked Toast catalog were reviewed for positive allergen signals. The sources are not a complete allergen matrix or cross-contact disclosure.",
      "evidence": [
        {
          "sourceKind": "restaurant-issued-menu-text",
          "sourceUrl": "https://www.anjurestaurant.com/happy-hour",
          "text": "Happy Hour — Bulgogi Frito Pie — bulgogi, kimchi slaw, lime sour cream, scallions, sesame seeds, crispy onions"
        }
      ]
    },
    {
      "id": "fried-chicken",
      "name": "Fried Chicken",
      "category": "Happy Hour",
      "description": "gochujang glaze, white BBQ",
      "ingredientsText": "gochujang glaze, white BBQ",
      "prices": [
        {
          "menuKind": "happy-hour",
          "text": "$8"
        }
      ],
      "menuKinds": [
        "happy-hour"
      ],
      "inlineModifiers": [],
      "isConfigurable": false,
      "allergens": [],
      "mayContain": [],
      "allergenSourceType": "unavailable",
      "sourceType": "restaurant-issued-menu-text",
      "sourceUrls": [
        "https://www.anjurestaurant.com/happy-hour"
      ],
      "sourceSummary": "Anju's current restaurant-issued menu does not provide enough item-level detail to assign a fixed major-allergen signal. Missing terms are not negative assurances, and no may-contain claim is invented.",
      "evidence": [
        {
          "sourceKind": "restaurant-issued-menu-text",
          "sourceUrl": "https://www.anjurestaurant.com/happy-hour",
          "text": "Happy Hour — Fried Chicken — gochujang glaze, white BBQ"
        }
      ]
    },
    {
      "id": "perilla-noodles",
      "name": "Perilla Noodles",
      "category": "Happy Hour",
      "description": "chilled buckwheat noodles tossed in perilla & roasted gim vinaigrette",
      "ingredientsText": "chilled buckwheat noodles tossed in perilla & roasted gim vinaigrette",
      "prices": [
        {
          "menuKind": "happy-hour",
          "text": "$6"
        }
      ],
      "menuKinds": [
        "happy-hour"
      ],
      "inlineModifiers": [],
      "isConfigurable": false,
      "allergens": [],
      "mayContain": [],
      "allergenSourceType": "unavailable",
      "sourceType": "restaurant-issued-menu-text",
      "sourceUrls": [
        "https://www.anjurestaurant.com/happy-hour"
      ],
      "sourceSummary": "Anju's current restaurant-issued menu does not provide enough item-level detail to assign a fixed major-allergen signal. Missing terms are not negative assurances, and no may-contain claim is invented.",
      "evidence": [
        {
          "sourceKind": "restaurant-issued-menu-text",
          "sourceUrl": "https://www.anjurestaurant.com/happy-hour",
          "text": "Happy Hour — Perilla Noodles — chilled buckwheat noodles tossed in perilla & roasted gim vinaigrette"
        }
      ]
    },
    {
      "id": "pork-and-kimchi-sausage",
      "name": "Pork & Kimchi Sausage",
      "category": "Happy Hour",
      "description": "house-made pork & kimchi sausage, gyeoja, sautéed peppers, onions",
      "ingredientsText": "house-made pork & kimchi sausage, gyeoja, sautéed peppers, onions",
      "prices": [
        {
          "menuKind": "happy-hour",
          "text": "$10"
        }
      ],
      "menuKinds": [
        "happy-hour"
      ],
      "inlineModifiers": [],
      "isConfigurable": false,
      "allergens": [],
      "mayContain": [],
      "allergenSourceType": "unavailable",
      "sourceType": "restaurant-issued-menu-text",
      "sourceUrls": [
        "https://www.anjurestaurant.com/happy-hour"
      ],
      "sourceSummary": "Anju's current restaurant-issued menu does not provide enough item-level detail to assign a fixed major-allergen signal. Missing terms are not negative assurances, and no may-contain claim is invented.",
      "evidence": [
        {
          "sourceKind": "restaurant-issued-menu-text",
          "sourceUrl": "https://www.anjurestaurant.com/happy-hour",
          "text": "Happy Hour — Pork & Kimchi Sausage — house-made pork & kimchi sausage, gyeoja, sautéed peppers, onions"
        }
      ]
    },
    {
      "id": "ramyun-spiced-nuts",
      "name": "Ramyun-Spiced Nuts",
      "category": "Happy Hour",
      "description": "house-made toasted nut mix seasoned with savory ramyun spices",
      "ingredientsText": "house-made toasted nut mix seasoned with savory ramyun spices",
      "prices": [
        {
          "menuKind": "happy-hour",
          "text": "$4"
        }
      ],
      "menuKinds": [
        "happy-hour"
      ],
      "inlineModifiers": [],
      "isConfigurable": false,
      "allergens": [],
      "mayContain": [],
      "allergenSourceType": "unavailable",
      "sourceType": "restaurant-issued-menu-text",
      "sourceUrls": [
        "https://www.anjurestaurant.com/happy-hour"
      ],
      "sourceSummary": "Anju's current restaurant-issued menu does not provide enough item-level detail to assign a fixed major-allergen signal. Missing terms are not negative assurances, and no may-contain claim is invented.",
      "evidence": [
        {
          "sourceKind": "restaurant-issued-menu-text",
          "sourceUrl": "https://www.anjurestaurant.com/happy-hour",
          "text": "Happy Hour — Ramyun-Spiced Nuts — house-made toasted nut mix seasoned with savory ramyun spices"
        }
      ]
    },
    {
      "id": "korean-maxx",
      "name": "Korean MAXX",
      "category": "Beverages",
      "description": "instant iced coffee, strong and sweet",
      "ingredientsText": "instant iced coffee, strong and sweet",
      "prices": [
        {
          "menuKind": "brunch",
          "text": "4"
        }
      ],
      "menuKinds": [
        "brunch"
      ],
      "inlineModifiers": [],
      "isConfigurable": false,
      "allergens": [],
      "mayContain": [],
      "allergenSourceType": "unavailable",
      "sourceType": "restaurant-issued-menu-text",
      "sourceUrls": [
        "https://www.anjurestaurant.com/brunch"
      ],
      "sourceSummary": "Anju's current restaurant-issued menu does not provide enough item-level detail to assign a fixed major-allergen signal. Missing terms are not negative assurances, and no may-contain claim is invented.",
      "evidence": [
        {
          "sourceKind": "restaurant-issued-menu-text",
          "sourceUrl": "https://www.anjurestaurant.com/brunch",
          "text": "Beverages — Korean MAXX — instant iced coffee, strong and sweet"
        }
      ]
    },
    {
      "id": "la-colombe-cold-brew",
      "name": "La Colombe Cold Brew",
      "category": "Beverages",
      "description": null,
      "ingredientsText": null,
      "prices": [
        {
          "menuKind": "brunch",
          "text": "4"
        }
      ],
      "menuKinds": [
        "brunch"
      ],
      "inlineModifiers": [],
      "isConfigurable": false,
      "allergens": [],
      "mayContain": [],
      "allergenSourceType": "unavailable",
      "sourceType": "restaurant-issued-menu-text",
      "sourceUrls": [
        "https://www.anjurestaurant.com/brunch"
      ],
      "sourceSummary": "Anju's current restaurant-issued menu does not provide enough item-level detail to assign a fixed major-allergen signal. Missing terms are not negative assurances, and no may-contain claim is invented.",
      "evidence": [
        {
          "sourceKind": "restaurant-issued-menu-text",
          "sourceUrl": "https://www.anjurestaurant.com/brunch",
          "text": "Beverages — La Colombe Cold Brew"
        }
      ]
    },
    {
      "id": "saam-jang-blood-mary",
      "name": "Saam Jang Blood Mary",
      "category": "Beverages",
      "description": "tomato juice, saam jang, fresh horseradish",
      "ingredientsText": "tomato juice, saam jang, fresh horseradish",
      "prices": [
        {
          "menuKind": "brunch",
          "text": "8"
        }
      ],
      "menuKinds": [
        "brunch"
      ],
      "inlineModifiers": [],
      "isConfigurable": false,
      "allergens": [],
      "mayContain": [],
      "allergenSourceType": "unavailable",
      "sourceType": "restaurant-issued-menu-text",
      "sourceUrls": [
        "https://www.anjurestaurant.com/brunch"
      ],
      "sourceSummary": "Anju's current restaurant-issued menu does not provide enough item-level detail to assign a fixed major-allergen signal. Missing terms are not negative assurances, and no may-contain claim is invented.",
      "evidence": [
        {
          "sourceKind": "restaurant-issued-menu-text",
          "sourceUrl": "https://www.anjurestaurant.com/brunch",
          "text": "Beverages — Saam Jang Blood Mary — tomato juice, saam jang, fresh horseradish"
        }
      ]
    },
    {
      "id": "strawberry-and-lychee-lemonade",
      "name": "Strawberry & Lychee Lemonade",
      "category": "Beverages",
      "description": "pureed fresh strawberry and lychee with fresh lemon juice",
      "ingredientsText": "pureed fresh strawberry and lychee with fresh lemon juice",
      "prices": [
        {
          "menuKind": "brunch",
          "text": "8"
        }
      ],
      "menuKinds": [
        "brunch"
      ],
      "inlineModifiers": [],
      "isConfigurable": false,
      "allergens": [],
      "mayContain": [],
      "allergenSourceType": "unavailable",
      "sourceType": "restaurant-issued-menu-text",
      "sourceUrls": [
        "https://www.anjurestaurant.com/brunch"
      ],
      "sourceSummary": "Anju's current restaurant-issued menu does not provide enough item-level detail to assign a fixed major-allergen signal. Missing terms are not negative assurances, and no may-contain claim is invented.",
      "evidence": [
        {
          "sourceKind": "restaurant-issued-menu-text",
          "sourceUrl": "https://www.anjurestaurant.com/brunch",
          "text": "Beverages — Strawberry & Lychee Lemonade — pureed fresh strawberry and lychee with fresh lemon juice"
        }
      ]
    }
  ]
}
